{
    "asset": {
        "format": "jpg",
        "id": "5eb0a7dee46aad84a292e17cbcd34531",
        "name": "000002.jpg",
        "path": "file:/Users/cyberbrain/Desktop/resize_image_dog/000002.jpg",
        "size": {
            "width": 300,
            "height": 300
        },
        "state": 2,
        "type": 1
    },
    "regions": [
        {
            "id": "rLGercafG",
            "type": "RECTANGLE",
            "tags": [
                "dog"
            ],
            "boundingBox": {
                "height": 232.7388768007203,
                "width": 253.46826230492198,
                "left": 18.946953781512605,
                "top": 2.5533650960384153
            },
            "points": [
                {
                    "x": 18.946953781512605,
                    "y": 2.5533650960384153
                },
                {
                    "x": 272.4152160864346,
                    "y": 2.5533650960384153
                },
                {
                    "x": 272.4152160864346,
                    "y": 235.29224189675872
                },
                {
                    "x": 18.946953781512605,
                    "y": 235.29224189675872
                }
            ]
        }
    ],
    "version": "2.1.0"
}