{
    "asset": {
        "format": "jpg",
        "id": "412c48ce4431d15eb7d5a68929b5425e",
        "name": "000002.jpg",
        "path": "file:/Users/cyberbrain/Desktop/resize_image_cat/000002.jpg",
        "size": {
            "width": 300,
            "height": 300
        },
        "state": 2,
        "type": 1
    },
    "regions": [
        {
            "id": "_JiIoq0B4",
            "type": "RECTANGLE",
            "tags": [
                "cat"
            ],
            "boundingBox": {
                "height": 278.546105942377,
                "width": 222.84054246698682,
                "left": 40.95231842737095,
                "top": 16.73685099039616
            },
            "points": [
                {
                    "x": 40.95231842737095,
                    "y": 16.73685099039616
                },
                {
                    "x": 263.7928608943578,
                    "y": 16.73685099039616
                },
                {
                    "x": 263.7928608943578,
                    "y": 295.2829569327731
                },
                {
                    "x": 40.95231842737095,
                    "y": 295.2829569327731
                }
            ]
        }
    ],
    "version": "2.1.0"
}